odoo8_addon_pos_customer_required-8.0.1.0.1.99.dev15-py3.8-nspkg.pth
odoo_addons/pos_customer_required/README.rst
odoo_addons/pos_customer_required/__init__.py
odoo_addons/pos_customer_required/__openerp__.py
odoo_addons/pos_customer_required/i18n/bg.po
odoo_addons/pos_customer_required/i18n/ca.po
odoo_addons/pos_customer_required/i18n/de.po
odoo_addons/pos_customer_required/i18n/el_GR.po
odoo_addons/pos_customer_required/i18n/es.po
odoo_addons/pos_customer_required/i18n/eu_ES.po
odoo_addons/pos_customer_required/i18n/fi.po
odoo_addons/pos_customer_required/i18n/fr.po
odoo_addons/pos_customer_required/i18n/gl.po
odoo_addons/pos_customer_required/i18n/hr.po
odoo_addons/pos_customer_required/i18n/it.po
odoo_addons/pos_customer_required/i18n/nl.po
odoo_addons/pos_customer_required/i18n/nl_NL.po
odoo_addons/pos_customer_required/i18n/pos_customer_required.pot
odoo_addons/pos_customer_required/i18n/pt_BR.po
odoo_addons/pos_customer_required/i18n/pt_PT.po
odoo_addons/pos_customer_required/i18n/sk.po
odoo_addons/pos_customer_required/i18n/sl.po
odoo_addons/pos_customer_required/i18n/tr.po
odoo_addons/pos_customer_required/i18n/zh_CN.po
odoo_addons/pos_customer_required/models/__init__.py
odoo_addons/pos_customer_required/models/pos.py
odoo_addons/pos_customer_required/static/description/icon.png
odoo_addons/pos_customer_required/static/src/js/pos_customer_required.js
odoo_addons/pos_customer_required/static/src/xml/templates.xml
odoo_addons/pos_customer_required/tests/__init__.py
odoo_addons/pos_customer_required/tests/test_pos.py
odoo_addons/pos_customer_required/views/pos_view.xml
odoo8_addon_pos_customer_required-8.0.1.0.1.99.dev15.dist-info/METADATA
odoo8_addon_pos_customer_required-8.0.1.0.1.99.dev15.dist-info/WHEEL
odoo8_addon_pos_customer_required-8.0.1.0.1.99.dev15.dist-info/namespace_packages.txt
odoo8_addon_pos_customer_required-8.0.1.0.1.99.dev15.dist-info/top_level.txt
odoo8_addon_pos_customer_required-8.0.1.0.1.99.dev15.dist-info/RECORD
