Metadata-Version: 2.1
Name: odoo8-addon-pos-customer-required
Version: 8.0.1.0.1.99.dev15
Summary: Point of Sale Require Customer
Home-page: http://www.apertoso.be
Author: Apertoso NV, Odoo Community Association (OCA)
Author-email: support@odoo-community.org
License: UNKNOWN
Platform: UNKNOWN
Classifier: Programming Language :: Python
Classifier: Framework :: Odoo
Classifier: Framework :: Odoo :: 8.0
Requires-Python: ~=2.7
Requires-Dist: odoo (<9.0a,>=8.0a)
